[
  {
    "slug": "fidha",
    "name": "Fidha",
    "id": "S001",
    "img": "https://i.postimg.cc/cLTPNWLc/Chat-GPT-Image-Sep-10-2025-11-32-32-PM.png",
    "year": "2025–26",
    "className": "Plus One Science",
    "section": "A",
    "batch": "Origin",
    "url": "/student.html?id=fidha"
  },
  {
    "slug": "devanandha",
    "name": "Devanandha",
    "id": "S002",
    "img": "https://i.postimg.cc/nz9W7QYd/Chat-GPT-Image-Sep-10-2025-11-51-26-PM.png",
    "year": "2025–26",
    "className": "Plus One Science",
    "section": "A",
    "batch": "Origin",
    "url": "/student.html?id=devanandha"
  },
  {
    "slug": "gayathri",
    "name": "Gayathri",
    "id": "S003",
    "img": "https://i.postimg.cc/cJbjrcYg/Chat-GPT-Image-Sep-10-2025-11-48-39-PM.png",
    "year": "2025–26",
    "className": "Plus One Science",
    "section": "A",
    "batch": "Origin",
    "url": "/student.html?id=gayathri"
  }
]
